{"team_id": 1610612749, "abbreviation": "MIL", "name": "Bucks", "city": "Milwaukee", "conference": "East", "division": "Central", "wins": 29, "losses": 45, "win_pct": 0.392, "playoff_rank": 11, "games_back": 0.0, "clinch_indicator": " - o", "home_record": "16-21", "road_record": "13-24", "conference_record": "20-27", "division_record": "9-6", "last_10": "2-8", "off_rating": 111.9, "def_rating": 118.2, "net_rating": -6.4, "pace": 98.36, "ts_pct": 0.588, "efg_pct": 0.564, "e_off_rating": 110.2, "e_def_rating": 116.6, "e_net_rating": -6.4, "e_pace": 99.8, "remaining_games": 8, "remaining_home": 4, "remaining_away": 4, "remaining_b2b_second_nights": 2, "points_pg": 110.4, "opp_points_pg": 116.9, "diff_points_pg": -6.4, "recent_win_pct": 0.2, "recent_avg_plus_minus": -16.5, "tanking_score": 0.268, "is_eliminated": true, "clinched_playoff": false, "clinched_division": false, "clinched_conference": false, "total_injured": 7, "players_out": 6, "players_out_longterm": 2, "players_day_to_day": 1, "injury_nr_adjustment": -2.2474122807017545, "h2h_records": {"ATL": {"wins": 1, "losses": 2, "point_diff": -13.0}, "BKN": {"wins": 1, "losses": 1, "point_diff": -14.0}, "BOS": {"wins": 1, "losses": 2, "point_diff": -13.333333333333334}, "CHA": {"wins": 3, "losses": 1, "point_diff": 3.25}, "CHI": {"wins": 3, "losses": 1, "point_diff": 4.5}, "CLE": {"wins": 1, "losses": 3, "point_diff": -5.5}, "DAL": {"wins": 1, "losses": 0, "point_diff": 2.0}, "DEN": {"wins": 0, "losses": 2, "point_diff": -3.0}, "DET": {"wins": 1, "losses": 2, "point_diff": -7.0}, "GSW": {"wins": 1, "losses": 1, "point_diff": 1.5}, "HOU": {"wins": 0, "losses": 1, "point_diff": -7.0}, "IND": {"wins": 4, "losses": 0, "point_diff": 9.0}, "LAC": {"wins": 0, "losses": 2, "point_diff": -23.5}, "LAL": {"wins": 1, "losses": 1, "point_diff": -10.0}, "MEM": {"wins": 0, "losses": 1, "point_diff": -21.0}, "MIA": {"wins": 1, "losses": 2, "point_diff": 0.3333333333333333}, "MIN": {"wins": 0, "losses": 2, "point_diff": -18.0}, "NOP": {"wins": 2, "losses": 0, "point_diff": 12.5}, "NYK": {"wins": 1, "losses": 2, "point_diff": -9.333333333333334}, "OKC": {"wins": 1, "losses": 1, "point_diff": -1.5}, "ORL": {"wins": 1, "losses": 2, "point_diff": -16.666666666666668}, "PHI": {"wins": 0, "losses": 3, "point_diff": -13.666666666666666}, "PHX": {"wins": 1, "losses": 1, "point_diff": -6.0}, "POR": {"wins": 0, "losses": 2, "point_diff": -21.5}, "SAC": {"wins": 1, "losses": 1, "point_diff": 7.5}, "SAS": {"wins": 0, "losses": 2, "point_diff": -25.0}, "TOR": {"wins": 1, "losses": 3, "point_diff": -14.0}, "UTA": {"wins": 1, "losses": 1, "point_diff": -9.0}, "WAS": {"wins": 1, "losses": 3, "point_diff": -0.25}}, "tov_pct": 0.152, "oreb_pct": 0.258, "ft_rate": 0.22339181286549709, "clutch_win_pct": 0.559, "clutch_plus_minus": 0.6, "playoff_experience": 682.1868435735832, "seed_probabilities": {"11": 0.7335, "12": 0.2665}, "projected_seed": 11, "projected_wins": 33.3, "projected_losses": 48.7, "playoff_prob": 0, "playin_prob": 0, "miss_prob": 1, "win_distribution": [{"wins": 29, "count": 16, "pct": 0.0016}, {"wins": 30, "count": 203, "pct": 0.0203}, {"wins": 31, "count": 754, "pct": 0.0754}, {"wins": 32, "count": 1869, "pct": 0.1869}, {"wins": 33, "count": 2671, "pct": 0.2671}, {"wins": 34, "count": 2568, "pct": 0.2568}, {"wins": 35, "count": 1415, "pct": 0.1415}, {"wins": 36, "count": 447, "pct": 0.0447}, {"wins": 37, "count": 57, "pct": 0.0057}], "game_predictions": [{"home_team": "MIL", "away_team": "DAL", "home_win_prob": 0.5951, "away_win_prob": 0.4049, "expected_margin": 1.7, "factors": [["Team strength (net rating)", -0.46], ["Home court", 1.5], ["Away B2B fatigue", 2.5], ["Home team tanking", -0.8], ["Away team tanking", 0.46], ["Recent form", -1.0]], "game_id": "0022500652", "game_date": "2026-03-31 00:00:00", "is_home": true, "opponent": "DAL", "win_prob": 0.5951}, {"home_team": "HOU", "away_team": "MIL", "home_win_prob": 0.5684, "away_win_prob": 0.4316, "expected_margin": 1.2, "factors": [["Team strength (net rating)", 3.78], ["Home court", 1.5], ["Home B2B fatigue", -2.5], ["Away B2B fatigue", 2.5], ["Away team tanking", 0.8], ["Injury differential", 3.2], ["Recent form", 3.0]], "game_id": "0022501110", "game_date": "2026-04-01 00:00:00", "is_home": false, "opponent": "HOU", "win_prob": 0.4316}, {"home_team": "MIL", "away_team": "BOS", "home_win_prob": 0.6245, "away_win_prob": 0.3755, "expected_margin": 2.3, "factors": [["Team strength (net rating)", -4.9], ["Home court", 1.5], ["Home team tanking", -0.8], ["Injury differential", -4.0], ["Away clinched (may rest)", 2.0], ["Recent form", -5.0]], "game_id": "0022501126", "game_date": "2026-04-03 00:00:00", "is_home": true, "opponent": "BOS", "win_prob": 0.6245}, {"home_team": "MIL", "away_team": "MEM", "home_win_prob": 0.5703, "away_win_prob": 0.4297, "expected_margin": 1.3, "factors": [["Team strength (net rating)", -0.7], ["Home court", 1.5], ["Home team tanking", -0.8], ["Away team tanking", 0.81], ["Injury differential", 1.6]], "game_id": "0022501135", "game_date": "2026-04-05 00:00:00", "is_home": true, "opponent": "MEM", "win_prob": 0.5703}, {"home_team": "BKN", "away_team": "MIL", "home_win_prob": 0.4796, "away_win_prob": 0.5204, "expected_margin": -0.4, "factors": [["Team strength (net rating)", -0.94], ["Home court", 1.5], ["Home team tanking", -0.84], ["Away team tanking", 0.8], ["Injury differential", 0.8], ["Recent form", -1.0]], "game_id": "0022501150", "game_date": "2026-04-07 00:00:00", "is_home": false, "opponent": "BKN", "win_prob": 0.5204}, {"home_team": "DET", "away_team": "MIL", "home_win_prob": 0.6924, "away_win_prob": 0.3076, "expected_margin": 3.7, "factors": [["Team strength (net rating)", 5.07], ["Home court", 1.5], ["Away B2B fatigue", 2.5], ["Away team tanking", 0.8], ["Injury differential", 0.8], ["Home clinched (may rest)", -2.0], ["Recent form", 5.0]], "game_id": "0022501160", "game_date": "2026-04-08 00:00:00", "is_home": false, "opponent": "DET", "win_prob": 0.3076}, {"home_team": "MIL", "away_team": "BKN", "home_win_prob": 0.6759, "away_win_prob": 0.3241, "expected_margin": 3.3, "factors": [["Team strength (net rating)", 0.94], ["Home court", 1.5], ["Away B2B fatigue", 2.5], ["Home team tanking", -0.8], ["Away team tanking", 0.84], ["Injury differential", -0.8], ["Recent form", 1.0]], "game_id": "0022501179", "game_date": "2026-04-10 00:00:00", "is_home": true, "opponent": "BKN", "win_prob": 0.6759}, {"home_team": "PHI", "away_team": "MIL", "home_win_prob": 0.4307, "away_win_prob": 0.5693, "expected_margin": -1.3, "factors": [["Team strength (net rating)", 2.1], ["Home court", 1.5], ["Away team tanking", 0.8], ["Injury differential", 4.0], ["Recent form", 4.0]], "game_id": "0022501191", "game_date": "2026-04-12 00:00:00", "is_home": false, "opponent": "PHI", "win_prob": 0.5693}], "monthly_trend": [{"team": "MIL", "month": "2025-10", "wins": 4, "losses": 1, "avg_plus_minus": 6.8, "win_pct": 0.8}, {"team": "MIL", "month": "2025-11", "wins": 5, "losses": 11, "avg_plus_minus": -5.0, "win_pct": 0.3125}, {"team": "MIL", "month": "2025-12", "wins": 5, "losses": 8, "avg_plus_minus": -3.923076923076923, "win_pct": 0.38461538461538464}, {"team": "MIL", "month": "2026-01", "wins": 4, "losses": 8, "avg_plus_minus": -7.25, "win_pct": 0.3333333333333333}, {"team": "MIL", "month": "2026-02", "wins": 8, "losses": 4, "avg_plus_minus": -1.5833333333333333, "win_pct": 0.6666666666666666}, {"team": "MIL", "month": "2026-03", "wins": 3, "losses": 13, "avg_plus_minus": -17.0625, "win_pct": 0.1875}], "likely_opponents": [], "roster": {"starters": [{"name": "Kevin Porter Jr.", "player_id": 1629645, "position": "G-F", "pts": 17.4, "reb": 5.2, "ast": 7.4, "fg_pct": 46.5, "min": 33.2, "headshot": "https://cdn.nba.com/headshots/nba/latest/260x190/1629645.png"}, {"name": "Ryan Rollins", "player_id": 1631157, "position": "G", "pts": 17.0, "reb": 4.6, "ast": 5.6, "fg_pct": 46.9, "min": 32.0, "headshot": "https://cdn.nba.com/headshots/nba/latest/260x190/1631157.png"}, {"name": "Giannis Antetokounmpo", "player_id": 203507, "position": "F", "pts": 27.6, "reb": 9.8, "ast": 5.4, "fg_pct": 62.4, "min": 28.9, "headshot": "https://cdn.nba.com/headshots/nba/latest/260x190/203507.png"}, {"name": "AJ Green", "player_id": 1631260, "position": "G", "pts": 9.6, "reb": 2.5, "ast": 1.9, "fg_pct": 41.7, "min": 28.5, "headshot": "https://cdn.nba.com/headshots/nba/latest/260x190/1631260.png"}, {"name": "Myles Turner", "player_id": 1626167, "position": "C-F", "pts": 11.9, "reb": 5.3, "ast": 1.5, "fg_pct": 43.9, "min": 27.1, "headshot": "https://cdn.nba.com/headshots/nba/latest/260x190/1626167.png"}], "bench_names": ["Kyle Kuzma", "Bobby Portis", "Taurean Prince", "Gary Trent Jr.", "Cam Thomas"], "bench_pts": 55.5, "coach": "Doc Rivers", "coach_record": "29-45"}}