{"today": "2026-04-18", "dates": ["2026-04-15", "2026-04-17", "2026-04-18", "2026-04-19", "2026-04-20", "2026-04-21"], "game_days": {"2026-04-15": [{"game_id": "0052500101", "game_date": "2026-04-15", "home_team": "PHI", "away_team": "ORL", "home_score": 109, "away_score": 97, "model_home_prob": 0.547, "vegas_spread": null, "vegas_home_prob": null, "edge": null, "status": "final", "winner": "PHI", "was_upset": false}, {"game_id": "0052500131", "game_date": "2026-04-15", "home_team": "LAC", "away_team": "GSW", "home_score": 121, "away_score": 126, "model_home_prob": 0.577, "vegas_spread": null, "vegas_home_prob": null, "edge": null, "status": "final", "winner": "GSW", "was_upset": true}], "2026-04-17": [{"game_id": "0052500211", "game_date": "2026-04-17", "home_team": "PHX", "away_team": "GSW", "home_score": 111, "away_score": 96, "model_home_prob": 0.58, "vegas_spread": null, "vegas_home_prob": null, "edge": null, "status": "final", "winner": "PHX", "was_upset": false}, {"game_id": "0052500201", "game_date": "2026-04-17", "home_team": "ORL", "away_team": "CHA", "home_score": 121, "away_score": 90, "model_home_prob": 0.5, "vegas_spread": null, "vegas_home_prob": null, "edge": null, "status": "final", "winner": "ORL", "was_upset": false}], "2026-04-18": [{"game_id": "0042500121", "game_date": "2026-04-18", "home_team": "NYK", "away_team": "ATL", "home_score": 113, "away_score": 102, "model_home_prob": 0.61, "vegas_spread": -5.5, "vegas_home_prob": 0.6613, "edge": -0.051, "status": "final", "winner": "NYK", "was_upset": false}, {"game_id": "0042500131", "game_date": "2026-04-18", "home_team": "CLE", "away_team": "TOR", "home_score": 126, "away_score": 113, "model_home_prob": 0.572, "vegas_spread": -8.5, "vegas_home_prob": 0.7595, "edge": -0.188, "status": "final", "winner": "CLE", "was_upset": false}, {"game_id": "0042500161", "game_date": "2026-04-18", "home_team": "DEN", "away_team": "MIN", "home_score": 116, "away_score": 105, "model_home_prob": 0.583, "vegas_spread": -6.5, "vegas_home_prob": 0.6854, "edge": -0.102, "status": "final", "winner": "DEN", "was_upset": false}, {"game_id": "0042500171", "game_date": "2026-04-18", "home_team": "LAL", "away_team": "HOU", "home_score": 107, "away_score": 98, "model_home_prob": 0.505, "vegas_spread": 4.5, "vegas_home_prob": 0.3752, "edge": 0.13, "status": "final", "winner": "LAL", "was_upset": false}], "2026-04-19": [{"game_id": "0042500101", "game_date": "2026-04-19", "home_team": "DET", "away_team": "ORL", "home_score": 0, "away_score": 0, "model_home_prob": 0.6348, "vegas_spread": -8.5, "vegas_home_prob": 0.7532, "edge": -0.118, "status": "scheduled", "winner": "", "implications": "ORL fighting for play-in spot"}, {"game_id": "0042500111", "game_date": "2026-04-19", "home_team": "BOS", "away_team": "PHI", "home_score": 0, "away_score": 0, "model_home_prob": 0.5993, "vegas_spread": -13.0, "vegas_home_prob": 0.8647, "edge": -0.265, "status": "scheduled", "winner": "", "implications": "PHI fighting for play-in spot"}, {"game_id": "0042500141", "game_date": "2026-04-19", "home_team": "OKC", "away_team": "PHX", "home_score": 0, "away_score": 0, "model_home_prob": 0.5292, "vegas_spread": -14.5, "vegas_home_prob": 0.887, "edge": -0.358, "status": "scheduled", "winner": "", "implications": "PHX fighting for play-in spot. Toss-up game"}, {"game_id": "0042500151", "game_date": "2026-04-19", "home_team": "SAS", "away_team": "POR", "home_score": 0, "away_score": 0, "model_home_prob": 0.5597, "vegas_spread": -11.0, "vegas_home_prob": 0.8152, "edge": -0.256, "status": "scheduled", "winner": "", "implications": "POR fighting for play-in spot"}], "2026-04-20": [{"game_id": "0042500162", "game_date": "2026-04-20", "home_team": "DEN", "away_team": "MIN", "home_score": 0, "away_score": 0, "model_home_prob": 0.5819, "vegas_spread": -6.5, "vegas_home_prob": 0.6854, "edge": -0.104, "status": "scheduled", "winner": "", "implications": "Playoff teams clash in the West"}, {"game_id": "0042500122", "game_date": "2026-04-20", "home_team": "NYK", "away_team": "ATL", "home_score": 0, "away_score": 0, "model_home_prob": 0.5616, "vegas_spread": -5.5, "vegas_home_prob": 0.6613, "edge": -0.1, "status": "scheduled", "winner": "", "implications": "Seed battle: #3-#5 in the East"}, {"game_id": "0042500132", "game_date": "2026-04-20", "home_team": "CLE", "away_team": "TOR", "home_score": 0, "away_score": 0, "model_home_prob": 0.6138, "vegas_spread": -8.5, "vegas_home_prob": 0.7595, "edge": -0.146, "status": "scheduled", "winner": "", "implications": "Seed battle: #4-#6 in the East"}], "2026-04-21": [{"game_id": "0042500152", "game_date": "2026-04-21", "home_team": "SAS", "away_team": "POR", "home_score": 0, "away_score": 0, "model_home_prob": 0.5594, "vegas_spread": -11.0, "vegas_home_prob": 0.8152, "edge": -0.256, "status": "scheduled", "winner": "", "implications": "POR fighting for play-in spot"}, {"game_id": "0042500172", "game_date": "2026-04-21", "home_team": "LAL", "away_team": "HOU", "home_score": 0, "away_score": 0, "model_home_prob": 0.5377, "vegas_spread": 4.5, "vegas_home_prob": 0.3752, "edge": 0.162, "status": "scheduled", "winner": "", "implications": "Seed battle: #4-#5 in the West. Toss-up game"}, {"game_id": "0042500112", "game_date": "2026-04-21", "home_team": "BOS", "away_team": "PHI", "home_score": 0, "away_score": 0, "model_home_prob": 0.5993, "vegas_spread": -13.0, "vegas_home_prob": 0.8647, "edge": -0.265, "status": "scheduled", "winner": "", "implications": "PHI fighting for play-in spot"}]}, "most_significant": [{"game_id": "0042500133", "game_date": "2026-04-23", "home_team": "TOR", "away_team": "CLE", "home_win_prob": 0.5131, "away_win_prob": 0.4869, "expected_margin": 0.2, "implications": "Seed battle: #4-#6 in the East. Toss-up game. Ripple effect on 6 teams", "impact_score": 16.69, "teams_affected": 6, "seed_shifts": 8, "affected_teams": ["ATL", "CLE", "NYK", "ORL", "PHI", "TOR"]}, {"game_id": "0042500134", "game_date": "2026-04-26", "home_team": "TOR", "away_team": "CLE", "home_win_prob": 0.5131, "away_win_prob": 0.4869, "expected_margin": 0.2, "implications": "Seed battle: #4-#6 in the East. Toss-up game. Ripple effect on 6 teams", "impact_score": 16.69, "teams_affected": 6, "seed_shifts": 8, "affected_teams": ["ATL", "CLE", "NYK", "ORL", "PHI", "TOR"]}, {"game_id": "0042500136", "game_date": "2026-05-01", "home_team": "TOR", "away_team": "CLE", "home_win_prob": 0.5131, "away_win_prob": 0.4869, "expected_margin": 0.2, "implications": "Seed battle: #4-#6 in the East. Toss-up game. Ripple effect on 6 teams", "impact_score": 16.69, "teams_affected": 6, "seed_shifts": 8, "affected_teams": ["ATL", "CLE", "NYK", "ORL", "PHI", "TOR"]}, {"game_id": "0042500132", "game_date": "2026-04-20", "home_team": "CLE", "away_team": "TOR", "home_win_prob": 0.6138, "away_win_prob": 0.3862, "expected_margin": 2.1, "implications": "Seed battle: #4-#6 in the East. Ripple effect on 6 teams", "impact_score": 14.29, "teams_affected": 6, "seed_shifts": 8, "affected_teams": ["ATL", "CLE", "NYK", "ORL", "PHI", "TOR"]}, {"game_id": "0042500135", "game_date": "2026-04-29", "home_team": "CLE", "away_team": "TOR", "home_win_prob": 0.6138, "away_win_prob": 0.3862, "expected_margin": 2.1, "implications": "Seed battle: #4-#6 in the East. Ripple effect on 6 teams", "impact_score": 14.29, "teams_affected": 6, "seed_shifts": 8, "affected_teams": ["ATL", "CLE", "NYK", "ORL", "PHI", "TOR"]}, {"game_id": "0042500137", "game_date": "2026-05-03", "home_team": "CLE", "away_team": "TOR", "home_win_prob": 0.6138, "away_win_prob": 0.3862, "expected_margin": 2.1, "implications": "Seed battle: #4-#6 in the East. Ripple effect on 6 teams", "impact_score": 14.29, "teams_affected": 6, "seed_shifts": 8, "affected_teams": ["ATL", "CLE", "NYK", "ORL", "PHI", "TOR"]}, {"game_id": "0042500113", "game_date": "2026-04-24", "home_team": "PHI", "away_team": "BOS", "home_win_prob": 0.5299, "away_win_prob": 0.4701, "expected_margin": 0.5, "implications": "PHI fighting for play-in spot. Toss-up game. Ripple effect on 4 teams", "impact_score": 13.41, "teams_affected": 4, "seed_shifts": 6, "affected_teams": ["ATL", "ORL", "PHI", "TOR"]}, {"game_id": "0042500114", "game_date": "2026-04-26", "home_team": "PHI", "away_team": "BOS", "home_win_prob": 0.5299, "away_win_prob": 0.4701, "expected_margin": 0.5, "implications": "PHI fighting for play-in spot. Toss-up game. Ripple effect on 4 teams", "impact_score": 13.41, "teams_affected": 4, "seed_shifts": 6, "affected_teams": ["ATL", "ORL", "PHI", "TOR"]}, {"game_id": "0042500116", "game_date": "2026-04-30", "home_team": "PHI", "away_team": "BOS", "home_win_prob": 0.5299, "away_win_prob": 0.4701, "expected_margin": 0.5, "implications": "PHI fighting for play-in spot. Toss-up game. Ripple effect on 4 teams", "impact_score": 13.41, "teams_affected": 4, "seed_shifts": 6, "affected_teams": ["ATL", "ORL", "PHI", "TOR"]}, {"game_id": "0042500111", "game_date": "2026-04-19", "home_team": "BOS", "away_team": "PHI", "home_win_prob": 0.5993, "away_win_prob": 0.4007, "expected_margin": 1.8, "implications": "PHI fighting for play-in spot. Ripple effect on 4 teams", "impact_score": 12.05, "teams_affected": 4, "seed_shifts": 6, "affected_teams": ["ATL", "ORL", "PHI", "TOR"]}, {"game_id": "0042500112", "game_date": "2026-04-21", "home_team": "BOS", "away_team": "PHI", "home_win_prob": 0.5993, "away_win_prob": 0.4007, "expected_margin": 1.8, "implications": "PHI fighting for play-in spot. Ripple effect on 4 teams", "impact_score": 12.05, "teams_affected": 4, "seed_shifts": 6, "affected_teams": ["ATL", "ORL", "PHI", "TOR"]}, {"game_id": "0042500115", "game_date": "2026-04-28", "home_team": "BOS", "away_team": "PHI", "home_win_prob": 0.5993, "away_win_prob": 0.4007, "expected_margin": 1.8, "implications": "PHI fighting for play-in spot. Ripple effect on 4 teams", "impact_score": 12.05, "teams_affected": 4, "seed_shifts": 6, "affected_teams": ["ATL", "ORL", "PHI", "TOR"]}, {"game_id": "0042500117", "game_date": "2026-05-02", "home_team": "BOS", "away_team": "PHI", "home_win_prob": 0.5993, "away_win_prob": 0.4007, "expected_margin": 1.8, "implications": "PHI fighting for play-in spot. Ripple effect on 4 teams", "impact_score": 12.05, "teams_affected": 4, "seed_shifts": 6, "affected_teams": ["ATL", "ORL", "PHI", "TOR"]}, {"game_id": "0042500122", "game_date": "2026-04-20", "home_team": "NYK", "away_team": "ATL", "home_win_prob": 0.5616, "away_win_prob": 0.4384, "expected_margin": 1.1, "implications": "Seed battle: #3-#5 in the East. Ripple effect on 5 teams", "impact_score": 11.88, "teams_affected": 5, "seed_shifts": 6, "affected_teams": ["ATL", "CLE", "NYK", "PHI", "TOR"]}, {"game_id": "0042500125", "game_date": "2026-04-28", "home_team": "NYK", "away_team": "ATL", "home_win_prob": 0.5616, "away_win_prob": 0.4384, "expected_margin": 1.1, "implications": "Seed battle: #3-#5 in the East. Ripple effect on 5 teams", "impact_score": 11.88, "teams_affected": 5, "seed_shifts": 6, "affected_teams": ["ATL", "CLE", "NYK", "PHI", "TOR"]}, {"game_id": "0042500127", "game_date": "2026-05-02", "home_team": "NYK", "away_team": "ATL", "home_win_prob": 0.5616, "away_win_prob": 0.4384, "expected_margin": 1.1, "implications": "Seed battle: #3-#5 in the East. Ripple effect on 5 teams", "impact_score": 11.88, "teams_affected": 5, "seed_shifts": 6, "affected_teams": ["ATL", "CLE", "NYK", "PHI", "TOR"]}, {"game_id": "0042500123", "game_date": "2026-04-23", "home_team": "ATL", "away_team": "NYK", "home_win_prob": 0.5822, "away_win_prob": 0.4178, "expected_margin": 1.5, "implications": "Seed battle: #3-#5 in the East. Ripple effect on 5 teams", "impact_score": 11.5, "teams_affected": 5, "seed_shifts": 6, "affected_teams": ["ATL", "CLE", "NYK", "PHI", "TOR"]}, {"game_id": "0042500124", "game_date": "2026-04-25", "home_team": "ATL", "away_team": "NYK", "home_win_prob": 0.5822, "away_win_prob": 0.4178, "expected_margin": 1.5, "implications": "Seed battle: #3-#5 in the East. Ripple effect on 5 teams", "impact_score": 11.5, "teams_affected": 5, "seed_shifts": 6, "affected_teams": ["ATL", "CLE", "NYK", "PHI", "TOR"]}, {"game_id": "0042500126", "game_date": "2026-04-30", "home_team": "ATL", "away_team": "NYK", "home_win_prob": 0.5822, "away_win_prob": 0.4178, "expected_margin": 1.5, "implications": "Seed battle: #3-#5 in the East. Ripple effect on 5 teams", "impact_score": 11.5, "teams_affected": 5, "seed_shifts": 6, "affected_teams": ["ATL", "CLE", "NYK", "PHI", "TOR"]}, {"game_id": "0042500103", "game_date": "2026-04-25", "home_team": "ORL", "away_team": "DET", "home_win_prob": 0.4486, "away_win_prob": 0.5514, "expected_margin": -0.9, "implications": "ORL fighting for play-in spot. Ripple effect on 3 teams", "impact_score": 9.28, "teams_affected": 3, "seed_shifts": 4, "affected_teams": ["ORL", "PHI", "TOR"]}]}